funkybomb/__init__.py
funkybomb/exceptions.py
funkybomb/node.py
funkybomb/util.py
funkybomb-0.1.dist-info/DESCRIPTION.rst
funkybomb-0.1.dist-info/METADATA
funkybomb-0.1.dist-info/RECORD
funkybomb-0.1.dist-info/WHEEL
funkybomb-0.1.dist-info/metadata.json
funkybomb-0.1.dist-info/top_level.txt
