Metadata-Version: 2.0
Name: funkybomb
Version: 0.1
Summary: Quick and wild HTML tree growth
Home-page: UNKNOWN
Author: Glenn Yonemitsu
Author-email: UNKNOWN
License: Apache License 2.0
Platform: UNKNOWN
Classifier: Development Status :: 3 - Alpha
Classifier: Environment :: Web Environment
Classifier: Intended Audience :: Developers
Classifier: License :: OSI Approved :: Apache Software License
Classifier: Programming Language :: Python :: 3.6
